.DS_Store
tccbsmig/__init__.py
tccbsmig/cbsapi.py
tccbsmig/ebs_en.py
tccbsmig-1.1b2.dist-info/LICENSE
tccbsmig-1.1b2.dist-info/METADATA
tccbsmig-1.1b2.dist-info/WHEEL
tccbsmig-1.1b2.dist-info/entry_points.txt
tccbsmig-1.1b2.dist-info/top_level.txt
tccbsmig-1.1b2.dist-info/RECORD
