Metadata-Version: 2.1
Name: tccbsmig
Version: 1.1b2
Summary: CBS Data Migration to Encrypted Disk
Home-page: UNKNOWN
Author: Minze Tao
Author-email: minzetaos@tencent.com
License: MIT
Keywords: Python CBS Ecryption Migration
Platform: UNKNOWN
Classifier: Programming Language :: Python :: 3
Classifier: License :: OSI Approved :: MIT License
Classifier: Operating System :: OS Independent
Requires-Dist: paramiko
Requires-Dist: tencentcloud-sdk-python
